{
  "resourceType": "CodeSystem",
  "status": "draft",
  "content": "complete",
  "name": "DeliveryTypeCS",
  "id": "delivery-type-cs",
  "title": "Art des Belieferung (CS)",
  "description": "Specifies how a dispense request should be fulfilled/ delivered",
  "url": "https://gematik.de/fhir/erp-servicerequest/CodeSystem/delivery-type-cs",
  "concept": [
    {
      "code": "pickup-by-healthcare-service",
      "display": "Abholung durch Pflegeeinrichtung"
    },
    {
      "code": "pickup-by-patient",
      "display": "Abholung durch Patient"
    },
    {
      "code": "delivery-to-healthcare-service",
      "display": "Lieferung an Pflegeeinrichtung"
    },
    {
      "code": "delivery-to-alternative-address",
      "display": "Lieferung an eine alternative Adresse"
    }
  ],
  "experimental": false,
  "publisher": "gematik GmbH",
  "version": "1.2.0-rc3",
  "date": "2025-01-01",
  "count": 4
}
